evaluationRecall/__init__.py
evaluationRecall/neighbors.py
evaluationRecall/neighbors_ivf.py
evaluationRecall/utils.py
evaluationRecall-0.5.dist-info/LICENSE
evaluationRecall-0.5.dist-info/METADATA
evaluationRecall-0.5.dist-info/WHEEL
evaluationRecall-0.5.dist-info/top_level.txt
evaluationRecall-0.5.dist-info/RECORD
