Metadata-Version: 2.1
Name: evaluationRecall
Version: 0.5
Summary: evaluationRecall
Home-page: https://github.com/jzhang-0/Quantization
Author: jzhang
License: UNKNOWN
Project-URL: Bug Tracker, https://github.com/jzhang-0/Quantization-Evaluation/issues
Platform: UNKNOWN
Requires-Python: >=3.6
License-File: LICENSE
